math3d/.DS_Store
math3d/__init__.py
math3d/__init__.pyi
math3d/linear_system.hpp
math3d/math3d.cpp
math3d/math3d.cpython-313-darwin.so
math3d/math3d.pyi
math3d/matrix.hpp
math3d/py.typed
math3d/test/README
math3d/test/__init__.py
math3d/test/bounds.py
math3d/test/remap_test.py
math3d/test/suzanne.obj
math3d/test/suzanne_normalized.obj
math3d/test/suzanne_unmapped.obj
math3d/test/triangle_test.py
math3d/types.hpp
math3d/util.h
math3d/vector.hpp
math3d_py-1.4.9.dist-info/METADATA
math3d_py-1.4.9.dist-info/WHEEL
math3d_py-1.4.9.dist-info/licenses/LICENSE.txt
math3d_py-1.4.9.dist-info/RECORD
