Metadata-Version: 2.2
Name: math3d_py
Version: 1.4.9
Summary: Python bindings for 3dmath
Author-Email: Murali Dhanakoti <dhanakoti.murali@gmail.com>
Requires-Python: <3.14,>=3.13
